zope.app.publication-5.1-py3.12-nspkg.pth
zope/app/publication/__init__.py
zope/app/publication/browser.py
zope/app/publication/configure.zcml
zope/app/publication/ftesting.zcml
zope/app/publication/ftp.py
zope/app/publication/http.py
zope/app/publication/httpfactory.py
zope/app/publication/httpfactory.rst
zope/app/publication/interfaces.py
zope/app/publication/meta.zcml
zope/app/publication/metaconfigure.py
zope/app/publication/metadirectives.py
zope/app/publication/methodnotallowed.rst
zope/app/publication/notfound.rst
zope/app/publication/publicationtraverse.py
zope/app/publication/requestpublicationfactories.py
zope/app/publication/requestpublicationregistry.py
zope/app/publication/site.rst
zope/app/publication/soap.py
zope/app/publication/testing.py
zope/app/publication/traversers.py
zope/app/publication/xmlrpc.py
zope/app/publication/zopepublication.py
zope/app/publication/tests/__init__.py
zope/app/publication/tests/ftest_zcml_dependencies.zcml
zope/app/publication/tests/support.py
zope/app/publication/tests/test_browserpublication.py
zope/app/publication/tests/test_dependencies.py
zope/app/publication/tests/test_functional.py
zope/app/publication/tests/test_http.py
zope/app/publication/tests/test_httpfactory.py
zope/app/publication/tests/test_proxycontrol.py
zope/app/publication/tests/test_requestpublicationfactories.py
zope/app/publication/tests/test_requestpublicationregistry.py
zope/app/publication/tests/test_simplecomponenttraverser.py
zope/app/publication/tests/test_xmlrpcpublication.py
zope/app/publication/tests/test_zopepublication.py
zope_app_publication-5.1.dist-info/licenses/LICENSE.rst
zope_app_publication-5.1.dist-info/METADATA
zope_app_publication-5.1.dist-info/WHEEL
zope_app_publication-5.1.dist-info/namespace_packages.txt
zope_app_publication-5.1.dist-info/top_level.txt
zope_app_publication-5.1.dist-info/RECORD
