Metadata-Version: 2.4
Name: zope.app.publication
Version: 5.1
Summary: Zope publication
Home-page: https://pypi.org/project/zope.app.publication/
Author: Zope Foundation and Contributors
Author-email: zope-dev@zope.dev
License: ZPL-2.1
Keywords: zope publication
Classifier: Development Status :: 5 - Production/Stable
Classifier: Environment :: Web Environment
Classifier: Intended Audience :: Developers
Classifier: License :: OSI Approved :: Zope Public License
Classifier: Programming Language :: Python :: 3
Classifier: Programming Language :: Python :: 3.9
Classifier: Programming Language :: Python :: 3.10
Classifier: Programming Language :: Python :: 3.11
Classifier: Programming Language :: Python :: 3.12
Classifier: Programming Language :: Python :: 3.13
Classifier: Programming Language :: Python :: Implementation :: CPython
Classifier: Programming Language :: Python :: Implementation :: PyPy
Classifier: Natural Language :: English
Classifier: Operating System :: OS Independent
Classifier: Topic :: Internet :: WWW/HTTP
Classifier: Framework :: Zope :: 3
Requires-Python: >=3.9
License-File: LICENSE.rst
Requires-Dist: zope.interface
Requires-Dist: zope.authentication
Requires-Dist: zope.component
Requires-Dist: zope.error
Requires-Dist: zope.browser>=1.2
Requires-Dist: zope.location
Requires-Dist: zope.publisher>=4.0.0a2
Requires-Dist: zope.traversing>=4.0.0a2
Requires-Dist: zope.i18n>=4.0.0a3
Requires-Dist: transaction>=1.1.0
Requires-Dist: setuptools
Provides-Extra: test
Requires-Dist: zope.annotation; extra == "test"
Requires-Dist: zope.app.appsetup>=3.14.0; extra == "test"
Requires-Dist: zope.app.http>=4.0; extra == "test"
Requires-Dist: zope.app.wsgi[testlayer]>=4.3; extra == "test"
Requires-Dist: zope.applicationcontrol>=4.0.0a1; extra == "test"
Requires-Dist: zope.browserpage; extra == "test"
Requires-Dist: zope.login; extra == "test"
Requires-Dist: zope.password; extra == "test"
Requires-Dist: zope.principalregistry; extra == "test"
Requires-Dist: zope.securitypolicy; extra == "test"
Requires-Dist: zope.site>=4.0.0a1; extra == "test"
Requires-Dist: zope.testing; extra == "test"
Requires-Dist: zope.testrunner; extra == "test"
Requires-Dist: ZODB>=5.1; extra == "test"
Dynamic: author
Dynamic: author-email
Dynamic: classifier
Dynamic: description
Dynamic: home-page
Dynamic: keywords
Dynamic: license
Dynamic: license-file
Dynamic: provides-extra
Dynamic: requires-dist
Dynamic: requires-python
Dynamic: summary
